[
  {
    "country": "Uruguay",
    "target": "Advance",
    "value": 0.692307692,
    "color": "yellowgreen",
    "group": "A"
  },
  {
    "country": "Saudi Arabia",
    "target": "Advance",
    "value": 0.153846154,
    "color": "darkblue",
    "group": "A"
  },
  {
    "country": "Russia",
    "target": "Advance",
    "value": 0.076923077,
    "color": "gold",
    "group": "A"
  },
  {
    "country": "Egypt",
    "target": "Advance",
    "value": 0.076923077,
    "color": "orange",
    "group": "A"
  },
  {
    "country": "Spain",
    "target": "Advance",
    "value": 0.027027027,
    "color": "yellowgreen",
    "group": "B"
  },
  {
    "country": "Portugal",
    "target": "Advance",
    "value": 0.324324324,
    "color": "darkblue",
    "group": "B"
  },
  {
    "country": "Morocco",
    "target": "Advance",
    "value": 0.472972973,
    "color": "gold",
    "group": "B"
  },
  {
    "country": "Iran",
    "target": "Advance",
    "value": 0.175675676,
    "color": "orange",
    "group": "B"
  },
  {
    "country": "Peru",
    "target": "Advance",
    "value": 0.344086022,
    "color": "yellowgreen",
    "group": "C"
  },
  {
    "country": "France",
    "target": "Advance",
    "value": 0.333333333,
    "color": "darkblue",
    "group": "C"
  },
  {
    "country": "Denmark",
    "target": "Advance",
    "value": 0.258064516,
    "color": "gold",
    "group": "C"
  },
  {
    "country": "Australia",
    "target": "Advance",
    "value": 0.064516129,
    "color": "orange",
    "group": "C"
  },
  {
    "country": "Nigeria",
    "target": "Advance",
    "value": 0.377358491,
    "color": "yellowgreen",
    "group": "D"
  },
  {
    "country": "Iceland",
    "target": "Advance",
    "value": 0.264150943,
    "color": "darkblue",
    "group": "D"
  },
  {
    "country": "Croatia",
    "target": "Advance",
    "value": 0.169811321,
    "color": "gold",
    "group": "D"
  },
  {
    "country": "Argentina",
    "target": "Advance",
    "value": 0.188679245,
    "color": "orange",
    "group": "D"
  },
  {
    "country": "Switzerland",
    "target": "Advance",
    "value": 0.583333333,
    "color": "yellowgreen",
    "group": "E"
  },
  {
    "country": "Serbia",
    "target": "Advance",
    "value": 0.226190476,
    "color": "darkblue",
    "group": "E"
  },
  {
    "country": "Costa Rica",
    "target": "Advance",
    "value": 0.154761905,
    "color": "gold",
    "group": "E"
  },
  {
    "country": "Brazil",
    "target": "Advance",
    "value": 0.035714286,
    "color": "orange",
    "group": "E"
  },
  {
    "country": "Sweden",
    "target": "Advance",
    "value": 0.308510638,
    "color": "yellowgreen",
    "group": "F"
  },
  {
    "country": "South Korea",
    "target": "Advance",
    "value": 0.329787234,
    "color": "darkblue",
    "group": "F"
  },
  {
    "country": "Mexico",
    "target": "Advance",
    "value": 0.329787234,
    "color": "gold",
    "group": "F"
  },
  {
    "country": "Germany",
    "target": "Advance",
    "value": 0.031914894,
    "color": "orange",
    "group": "F"
  },
  {
    "country": "Tunisia",
    "target": "Advance",
    "value": 0.419354839,
    "color": "yellowgreen",
    "group": "G"
  },
  {
    "country": "Panama",
    "target": "Advance",
    "value": 0.204301075,
    "color": "darkblue",
    "group": "G"
  },
  {
    "country": "England",
    "target": "Advance",
    "value": 0.161290323,
    "color": "gold",
    "group": "G"
  },
  {
    "country": "Belgium",
    "target": "Advance",
    "value": 0.215053763,
    "color": "orange",
    "group": "G"
  },
  {
    "country": "Senegal",
    "target": "Advance",
    "value": 0.186813187,
    "color": "yellowgreen",
    "group": "H"
  },
  {
    "country": "Poland",
    "target": "Advance",
    "value": 0.505494505,
    "color": "darkblue",
    "group": "H"
  },
  {
    "country": "Japan",
    "target": "Advance",
    "value": 0.032967033,
    "color": "gold",
    "group": "H"
  },
  {
    "country": "Colombia",
    "target": "Advance",
    "value": 0.274725275,
    "color": "orange",
    "group": "H"
  },
  {
    "country": "Uruguay",
    "target": "Out",
    "value": 0.307692308,
    "color": "yellowgreen",
    "group": "A"
  },
  {
    "country": "Saudi Arabia",
    "target": "Out",
    "value": 0.846153846,
    "color": "darkblue",
    "group": "A"
  },
  {
    "country": "Russia",
    "target": "Out",
    "value": 0.923076923,
    "color": "gold",
    "group": "A"
  },
  {
    "country": "Egypt",
    "target": "Out",
    "value": 0.923076923,
    "color": "orange",
    "group": "A"
  },
  {
    "country": "Spain",
    "target": "Out",
    "value": 0.972972973,
    "color": "yellowgreen",
    "group": "B"
  },
  {
    "country": "Portugal",
    "target": "Out",
    "value": 0.675675676,
    "color": "darkblue",
    "group": "B"
  },
  {
    "country": "Morocco",
    "target": "Out",
    "value": 0.527027027,
    "color": "gold",
    "group": "B"
  },
  {
    "country": "Iran",
    "target": "Out",
    "value": 0.824324324,
    "color": "orange",
    "group": "B"
  }
]
